huilintest-1.0.0.data/purelib/huilin/__init__.py
huilintest-1.0.0.data/purelib/huilin/myprint.py
huilintest-1.0.0.dist-info/METADATA
huilintest-1.0.0.dist-info/WHEEL
huilintest-1.0.0.dist-info/top_level.txt
huilintest-1.0.0.dist-info/RECORD
