Metadata-Version: 2.1
Name: huilintest
Version: 1.0.0
Summary: A print test for PyPI
Home-page: https://www.python.org/
Author: winycg
License: UNKNOWN
Platform: UNKNOWN
Requires-Python: >=3
